llm_data_processor/__init__.py
llm_data_processor/data_analyzer.py
llm_data_processor/data_augmenter.py
llm_data_processor/data_loader.py
llm_data_processor/data_preprocessor.py
llm_data_processor/utils.py
tests/__init__.py
tests/test_data_analyzer.py
tests/test_data_augmenter.py
tests/test_data_loader.py
tests/test_data_preprocessor.py
tests/test_utils.py
qullm-0.3.0.dist-info/LICENSE
qullm-0.3.0.dist-info/METADATA
qullm-0.3.0.dist-info/WHEEL
qullm-0.3.0.dist-info/entry_points.txt
qullm-0.3.0.dist-info/top_level.txt
qullm-0.3.0.dist-info/RECORD
