Metadata-Version: 2.1
Name: qullm
Version: 0.3.0
Summary: A Python package for preprocessing and augmenting data for large language models by quantum Neural networks.
Home-page: https://github.com/1nobodybutme1/qullm
Author: C.C.K Leon
Author-email: ckchau1@asu.edu
Classifier: Programming Language :: Python :: 3
Classifier: License :: OSI Approved :: MIT License
Classifier: Operating System :: OS Independent
Requires-Python: >=3.6
License-File: LICENSE
Requires-Dist: numpy
Requires-Dist: pandas
